py_global_shortcuts/__init__.py
py_global_shortcuts/filed_dict.py
py_global_shortcuts/globals.py
py_global_shortcuts/gnome_binder.py
py_global_shortcuts/linux_comms.py
py_global_shortcuts/pynput_binder.py
py_global_shortcuts/shortcut_binder.py
py_global_shortcuts/utilities.py
py_global_shortcuts-0.1.2.dist-info/METADATA
py_global_shortcuts-0.1.2.dist-info/WHEEL
py_global_shortcuts-0.1.2.dist-info/top_level.txt
py_global_shortcuts-0.1.2.dist-info/RECORD
