Metadata-Version: 2.4
Name: py-global-shortcuts
Version: 0.1.2
Summary: Python library for creating global keyboard shortcuts.
Requires-Python: >=3.10
Requires-Dist: pynput>=1.8.1
